df_generics/__init__.py
df_generics/response.py
df_generics-0.1.0.dist-info/LICENSE
df_generics-0.1.0.dist-info/METADATA
df_generics-0.1.0.dist-info/WHEEL
df_generics-0.1.0.dist-info/top_level.txt
df_generics-0.1.0.dist-info/RECORD
