Metadata-Version: 2.1
Name: df-generics
Version: 0.1.0
Summary: [There](https://github.com/deepmipt/dialog_flow_generics) is an addon for the [Dialog Flow Engine](https://github.com/deepmipt/dialog_flow_engine), a minimalistic open-source engine for conversational services.
Home-page: https://github.com/deepmipt/dialog_flow_generics
Author: Denis Kuznetsov
Author-email: kuznetsov.den.p@gmail.com
License: UNKNOWN
Keywords: chatbots,df-generics
Platform: UNKNOWN
Classifier: Development Status :: 2 - Pre-Alpha
Classifier: Intended Audience :: Developers
Classifier: Topic :: Software Development :: Build Tools
Classifier: License :: OSI Approved :: Apache Software License
Classifier: Operating System :: OS Independent
Classifier: Programming Language :: Python :: 3
Classifier: Programming Language :: Python :: 3.6
Classifier: Programming Language :: Python :: 3.7
Classifier: Programming Language :: Python :: 3.8
Classifier: Programming Language :: Python :: 3.9
Classifier: Programming Language :: Python :: 3 :: Only
Requires-Python: >=3.6, <4
License-File: LICENSE
Requires-Dist: df-engine (>=0.9.0)
